dataframe_generator/__init__.py
dataframe_generator/__main__.py
dataframe_generator/data_type.py
dataframe_generator/generator.py
dataframe_generator/outputter.py
dataframe_generator/struct_field.py
dataframe_generator/struct_type.py
dataframe_generator-0.1.0.dist-info/LICENSE
dataframe_generator-0.1.0.dist-info/WHEEL
dataframe_generator-0.1.0.dist-info/METADATA
dataframe_generator-0.1.0.dist-info/RECORD
