Metadata-Version: 2.1
Name: dataframe-generator
Version: 0.1.0
Summary: A simple Python module for generating test CSV datasets from PySpark schemas.
Author: Szabolcs Vasas
Author-email: vasas@apache.org
Requires-Python: >=3.7,<4.0
Classifier: Programming Language :: Python :: 3
Classifier: Programming Language :: Python :: 3.7
Classifier: Programming Language :: Python :: 3.8
